{
    "basePath": "/",
    "definitions": {
        "CommonResponse«HermesBillImportDetailInfoDto»": {
            "properties": {
                "errorCode": {
                    "description": "错误代码",
                    "format": "int32",
                    "type": "integer"
                },
                "errorMessage": {
                    "description": "错误描述信息",
                    "type": "string"
                },
                "results": {
                    "$ref": "#/definitions/HermesBillImportDetailInfoDto",
                    "description": "返回结果"
                },
                "status": {
                    "description": "处理状态： 0 正常状态或业务异常，1 系统异常",
                    "format": "int64",
                    "type": "integer"
                },
                "timeStamp": {
                    "description": "服务端返回请求结果的时间",
                    "format": "int64",
                    "type": "integer"
                }
            },
            "required": [
                "status",
                "timeStamp"
            ],
            "type": "object"
        },
        "CommonResponse«HermesBillTransactionNumberDto»": {
            "properties": {
                "errorCode": {
                    "description": "错误代码",
                    "format": "int32",
                    "type": "integer"
                },
                "errorMessage": {
                    "description": "错误描述信息",
                    "type": "string"
                },
                "results": {
                    "$ref": "#/definitions/HermesBillTransactionNumberDto",
                    "description": "返回结果"
                },
                "status": {
                    "description": "处理状态： 0 正常状态或业务异常，1 系统异常",
                    "format": "int64",
                    "type": "integer"
                },
                "timeStamp": {
                    "description": "服务端返回请求结果的时间",
                    "format": "int64",
                    "type": "integer"
                }
            },
            "required": [
                "status",
                "timeStamp"
            ],
            "type": "object"
        },
        "CommonResponse«PageDto«HermesBillAssignmentDto»»": {
            "properties": {
                "errorCode": {
                    "description": "错误代码",
                    "format": "int32",
                    "type": "integer"
                },
                "errorMessage": {
                    "description": "错误描述信息",
                    "type": "string"
                },
                "results": {
                    "$ref": "#/definitions/PageDto«HermesBillAssignmentDto»",
                    "description": "返回结果"
                },
                "status": {
                    "description": "处理状态： 0 正常状态或业务异常，1 系统异常",
                    "format": "int64",
                    "type": "integer"
                },
                "timeStamp": {
                    "description": "服务端返回请求结果的时间",
                    "format": "int64",
                    "type": "integer"
                }
            },
            "required": [
                "status",
                "timeStamp"
            ],
            "type": "object"
        },
        "CommonResponse«PageDto«HermesBillImportInfoDto»»": {
            "properties": {
                "errorCode": {
                    "description": "错误代码",
                    "format": "int32",
                    "type": "integer"
                },
                "errorMessage": {
                    "description": "错误描述信息",
                    "type": "string"
                },
                "results": {
                    "$ref": "#/definitions/PageDto«HermesBillImportInfoDto»",
                    "description": "返回结果"
                },
                "status": {
                    "description": "处理状态： 0 正常状态或业务异常，1 系统异常",
                    "format": "int64",
                    "type": "integer"
                },
                "timeStamp": {
                    "description": "服务端返回请求结果的时间",
                    "format": "int64",
                    "type": "integer"
                }
            },
            "required": [
                "status",
                "timeStamp"
            ],
            "type": "object"
        },
        "CommonResponse«PageDto«HermesBillResultDto»»": {
            "properties": {
                "errorCode": {
                    "description": "错误代码",
                    "format": "int32",
                    "type": "integer"
                },
                "errorMessage": {
                    "description": "错误描述信息",
                    "type": "string"
                },
                "results": {
                    "$ref": "#/definitions/PageDto«HermesBillResultDto»",
                    "description": "返回结果"
                },
                "status": {
                    "description": "处理状态： 0 正常状态或业务异常，1 系统异常",
                    "format": "int64",
                    "type": "integer"
                },
                "timeStamp": {
                    "description": "服务端返回请求结果的时间",
                    "format": "int64",
                    "type": "integer"
                }
            },
            "required": [
                "status",
                "timeStamp"
            ],
            "type": "object"
        },
        "CommonResponse«PageDto«HermesBillSystemInfoDto»»": {
            "properties": {
                "errorCode": {
                    "description": "错误代码",
                    "format": "int32",
                    "type": "integer"
                },
                "errorMessage": {
                    "description": "错误描述信息",
                    "type": "string"
                },
                "results": {
                    "$ref": "#/definitions/PageDto«HermesBillSystemInfoDto»",
                    "description": "返回结果"
                },
                "status": {
                    "description": "处理状态： 0 正常状态或业务异常，1 系统异常",
                    "format": "int64",
                    "type": "integer"
                },
                "timeStamp": {
                    "description": "服务端返回请求结果的时间",
                    "format": "int64",
                    "type": "integer"
                }
            },
            "required": [
                "status",
                "timeStamp"
            ],
            "type": "object"
        },
        "CommonResponse«PageDto«HermesSapBillInfo»»": {
            "properties": {
                "errorCode": {
                    "description": "错误代码",
                    "format": "int32",
                    "type": "integer"
                },
                "errorMessage": {
                    "description": "错误描述信息",
                    "type": "string"
                },
                "results": {
                    "$ref": "#/definitions/PageDto«HermesSapBillInfo»",
                    "description": "返回结果"
                },
                "status": {
                    "description": "处理状态： 0 正常状态或业务异常，1 系统异常",
                    "format": "int64",
                    "type": "integer"
                },
                "timeStamp": {
                    "description": "服务端返回请求结果的时间",
                    "format": "int64",
                    "type": "integer"
                }
            },
            "required": [
                "status",
                "timeStamp"
            ],
            "type": "object"
        },
        "CommonResponse«boolean»": {
            "properties": {
                "errorCode": {
                    "description": "错误代码",
                    "format": "int32",
                    "type": "integer"
                },
                "errorMessage": {
                    "description": "错误描述信息",
                    "type": "string"
                },
                "results": {
                    "description": "返回结果",
                    "example": false,
                    "type": "boolean"
                },
                "status": {
                    "description": "处理状态： 0 正常状态或业务异常，1 系统异常",
                    "format": "int64",
                    "type": "integer"
                },
                "timeStamp": {
                    "description": "服务端返回请求结果的时间",
                    "format": "int64",
                    "type": "integer"
                }
            },
            "required": [
                "status",
                "timeStamp"
            ],
            "type": "object"
        },
        "CommonResponse«对账结果详情»": {
            "properties": {
                "errorCode": {
                    "description": "错误代码",
                    "format": "int32",
                    "type": "integer"
                },
                "errorMessage": {
                    "description": "错误描述信息",
                    "type": "string"
                },
                "results": {
                    "$ref": "#/definitions/对账结果详情",
                    "description": "返回结果"
                },
                "status": {
                    "description": "处理状态： 0 正常状态或业务异常，1 系统异常",
                    "format": "int64",
                    "type": "integer"
                },
                "timeStamp": {
                    "description": "服务端返回请求结果的时间",
                    "format": "int64",
                    "type": "integer"
                }
            },
            "required": [
                "status",
                "timeStamp"
            ],
            "type": "object"
        },
        "HermesBillAssignmentDto": {
            "properties": {
                "assignmentId": {
                    "description": "主键",
                    "format": "int64",
                    "type": "integer"
                },
                "content": {
                    "description": "内容",
                    "type": "string"
                },
                "createOp": {
                    "description": "操作人",
                    "type": "string"
                },
                "createTime": {
                    "format": "date-time",
                    "type": "string"
                },
                "salesOrderNumber": {
                    "description": "SALES订单号",
                    "type": "string"
                },
                "status": {
                    "description": "状态",
                    "type": "string"
                },
                "type": {
                    "description": "标题",
                    "type": "string"
                },
                "updateOp": {
                    "description": "处理人",
                    "type": "string"
                }
            },
            "type": "object"
        },
        "HermesBillAssignmentQueryDto": {
            "description": "对账任务查询",
            "properties": {
                "createOp": {
                    "description": "操作人",
                    "type": "string"
                },
                "pageNo": {
                    "description": "页码",
                    "format": "int32",
                    "type": "integer"
                },
                "pageSize": {
                    "description": "每页显示条数",
                    "format": "int32",
                    "type": "integer"
                },
                "updateOp": {
                    "description": "处理人",
                    "type": "string"
                }
            },
            "type": "object"
        },
        "HermesBillAssignmentUpdateDto": {
            "description": "对账任务处理",
            "properties": {
                "assignmentId": {
                    "description": "对账任务主键",
                    "format": "int64",
                    "type": "integer"
                },
                "remark": {
                    "description": "备注",
                    "type": "string"
                },
                "type": {
                    "description": "操作类型(REVIEW：处理完毕，返回复审/CLOSE：流程终止，忽略异常)",
                    "type": "string"
                }
            },
            "type": "object"
        },
        "HermesBillImportDetailInfoDto": {
            "description": "对账日志详情信息",
            "properties": {
                "content": {
                    "description": "日志内容",
                    "items": {
                        "type": "string"
                    },
                    "type": "array"
                },
                "createTime": {
                    "description": "创建时间",
                    "format": "date-time",
                    "type": "string"
                },
                "title": {
                    "description": "标题",
                    "type": "string"
                }
            },
            "type": "object"
        },
        "HermesBillImportInfoDto": {
            "description": "对账日志信息",
            "properties": {
                "createOp": {
                    "description": "操作人员",
                    "type": "string"
                },
                "createTime": {
                    "description": "创建时间",
                    "format": "date-time",
                    "type": "string"
                },
                "hermesBillImportInfoSysId": {
                    "description": "主键",
                    "format": "int64",
                    "type": "integer"
                },
                "platform": {
                    "description": "账单平台",
                    "format": "int32",
                    "type": "integer"
                },
                "status": {
                    "description": "状态",
                    "format": "int32",
                    "type": "integer"
                },
                "title": {
                    "description": "标题",
                    "type": "string"
                },
                "type": {
                    "description": "日志类型",
                    "format": "int32",
                    "type": "integer"
                }
            },
            "type": "object"
        },
        "HermesBillImportInfoQueryDto": {
            "description": "对账日志信息",
            "properties": {
                "createEndTime": {
                    "description": "创建终止时间",
                    "type": "string"
                },
                "createOp": {
                    "description": "操作人员",
                    "type": "string"
                },
                "createStartTime": {
                    "description": "创建开始时间",
                    "type": "string"
                },
                "pageNo": {
                    "description": "查询页",
                    "format": "int32",
                    "type": "integer"
                },
                "pageSize": {
                    "description": "每页记录数",
                    "format": "int32",
                    "type": "integer"
                },
                "status": {
                    "description": "状态",
                    "format": "int32",
                    "type": "integer"
                },
                "type": {
                    "description": "日志类型",
                    "format": "int32",
                    "type": "integer"
                }
            },
            "type": "object"
        },
        "HermesBillResultDto": {
            "properties": {
                "billResultId": {
                    "format": "int64",
                    "type": "integer"
                },
                "channelId": {
                    "type": "string"
                },
                "createOp": {
                    "type": "string"
                },
                "createTime": {
                    "format": "date-time",
                    "type": "string"
                },
                "eventTime": {
                    "format": "date-time",
                    "type": "string"
                },
                "orderTime": {
                    "format": "date-time",
                    "type": "string"
                },
                "salesOrderNumber": {
                    "type": "string"
                },
                "status": {
                    "type": "string"
                },
                "updateTime": {
                    "format": "date-time",
                    "type": "string"
                }
            },
            "type": "object"
        },
        "HermesBillSystemInfoDto": {
            "description": "账单管理信息",
            "properties": {
                "accountType": {
                    "description": "账目类型",
                    "format": "int32",
                    "type": "integer"
                },
                "accountTypeDescribe": {
                    "description": "账目类型描述",
                    "type": "string"
                },
                "billAmount": {
                    "description": "账单金额",
                    "format": "double",
                    "type": "number"
                },
                "billPlatform": {
                    "description": "账单平台",
                    "format": "int32",
                    "type": "integer"
                },
                "billType": {
                    "description": "账单类型",
                    "format": "int32",
                    "type": "integer"
                },
                "createTime": {
                    "description": "添加时间",
                    "format": "date-time",
                    "type": "string"
                },
                "currencyType": {
                    "description": "货币种类",
                    "type": "string"
                },
                "hermesBillSystemInfoSysId": {
                    "description": "主键自增",
                    "format": "int64",
                    "type": "integer"
                },
                "paymentTradingNumber": {
                    "description": "支付交易号",
                    "type": "string"
                },
                "salesOrderNumber": {
                    "description": "平台订单号",
                    "type": "string"
                },
                "superOrderId": {
                    "description": "SuperOrderId",
                    "format": "int64",
                    "type": "integer"
                },
                "transactionNumber": {
                    "description": "交易流水号(付款编号)",
                    "type": "string"
                },
                "transactionTime": {
                    "description": "交易时间",
                    "format": "date-time",
                    "type": "string"
                },
                "updateTime": {
                    "description": "更新时间",
                    "format": "date-time",
                    "type": "string"
                }
            },
            "type": "object"
        },
        "HermesBillSystemInfoQueryDto": {
            "properties": {
                "accountType": {
                    "description": "账目类型",
                    "format": "int32",
                    "type": "integer"
                },
                "billPlatform": {
                    "description": "账单平台",
                    "format": "int32",
                    "type": "integer"
                },
                "billType": {
                    "description": "账单类型",
                    "format": "int32",
                    "type": "integer"
                },
                "createEndTime": {
                    "description": "添加结束时间",
                    "type": "string"
                },
                "createStartTime": {
                    "description": "添加开始时间",
                    "type": "string"
                },
                "orderNumber": {
                    "description": "平台订单号",
                    "type": "string"
                },
                "orderNumberType": {
                    "description": "订单号类型 1-平台订单号  2-SuperOrderId",
                    "format": "int32",
                    "type": "integer"
                },
                "pageNo": {
                    "format": "int32",
                    "type": "integer"
                },
                "pageSize": {
                    "format": "int32",
                    "type": "integer"
                },
                "paymentTradingNumber": {
                    "description": "支付交易号",
                    "type": "string"
                },
                "transactionEndTime": {
                    "description": "交易结束时间",
                    "type": "string"
                },
                "transactionNumber": {
                    "description": "交易流水号(付款编号)",
                    "type": "string"
                },
                "transactionStartTime": {
                    "description": "交易开始时间",
                    "type": "string"
                }
            },
            "type": "object"
        },
        "HermesBillTransactionNumberDto": {
            "description": "定位交易流水信息",
            "properties": {
                "flag": {
                    "description": "定位标识",
                    "example": false,
                    "type": "boolean"
                },
                "paymentMethod": {
                    "description": "付款方式",
                    "type": "string"
                },
                "salesOrderNumber": {
                    "description": "平台订单号",
                    "type": "string"
                },
                "superOrderId": {
                    "description": "SuperOrderId",
                    "format": "int64",
                    "type": "integer"
                },
                "transactionNumber": {
                    "description": "交易流水号(付款编号)",
                    "type": "string"
                }
            },
            "type": "object"
        },
        "HermesExceptionUpdateDto": {
            "properties": {
                "billResultId": {
                    "description": "对账结果主键",
                    "format": "int64",
                    "type": "integer"
                },
                "remark": {
                    "description": "备注",
                    "type": "string"
                },
                "type": {
                    "description": "处理类型(NEXT：交由下一节点人处理IGNORE：忽略RETRY：重新校验)",
                    "type": "string"
                },
                "updateOp": {
                    "description": "下一节点处理人用户名",
                    "type": "string"
                }
            },
            "type": "object"
        },
        "HermesResultQueryDto": {
            "description": "对账结果查询",
            "properties": {
                "endTime": {
                    "description": "账单查询结束时间",
                    "format": "date-time",
                    "type": "string"
                },
                "pageNo": {
                    "description": "页码",
                    "format": "int32",
                    "type": "integer"
                },
                "pageSize": {
                    "description": "每页显示条数",
                    "format": "int32",
                    "type": "integer"
                },
                "startTime": {
                    "description": "账单查询开始时间",
                    "format": "date-time",
                    "type": "string"
                },
                "status": {
                    "description": "对账状态",
                    "type": "string"
                }
            },
            "type": "object"
        },
        "HermesSapBillInfo": {
            "properties": {
                "amountInLocalCurrency": {
                    "format": "double",
                    "type": "number"
                },
                "assignment": {
                    "type": "string"
                },
                "businessArea": {
                    "type": "string"
                },
                "clearingDocument": {
                    "type": "string"
                },
                "createOp": {
                    "type": "string"
                },
                "createTime": {
                    "format": "date-time",
                    "type": "string"
                },
                "documentHeaderText": {
                    "type": "string"
                },
                "documentNumber": {
                    "type": "string"
                },
                "documentType": {
                    "type": "string"
                },
                "fiscalYear": {
                    "type": "string"
                },
                "glAccount": {
                    "type": "string"
                },
                "hermesBillSapInfoSysId": {
                    "format": "int64",
                    "type": "integer"
                },
                "postingDate": {
                    "format": "date-time",
                    "type": "string"
                },
                "referenceKey": {
                    "type": "string"
                },
                "referenceKey3": {
                    "type": "string"
                },
                "text": {
                    "type": "string"
                },
                "updateOp": {
                    "type": "string"
                },
                "updateTime": {
                    "format": "date-time",
                    "type": "string"
                },
                "yearMonth": {
                    "type": "string"
                }
            },
            "type": "object"
        },
        "HermesSapBillInfoDto": {
            "properties": {
                "amountInLocalCurrency": {
                    "format": "double",
                    "type": "number"
                },
                "documentHeaderText": {
                    "type": "string"
                },
                "postingDate": {
                    "format": "date-time",
                    "type": "string"
                }
            },
            "type": "object"
        },
        "HermesSapBillInfoQueryDto": {
            "properties": {
                "documentHeaderText": {
                    "type": "string"
                },
                "endTime": {
                    "type": "string"
                },
                "pageNo": {
                    "format": "int32",
                    "type": "integer"
                },
                "pageSize": {
                    "format": "int32",
                    "type": "integer"
                },
                "startTime": {
                    "type": "string"
                }
            },
            "type": "object"
        },
        "PageDto«HermesBillAssignmentDto»": {
            "properties": {
                "pageNum": {
                    "format": "int64",
                    "type": "integer"
                },
                "pages": {
                    "format": "int64",
                    "type": "integer"
                },
                "records": {
                    "items": {
                        "$ref": "#/definitions/HermesBillAssignmentDto"
                    },
                    "type": "array"
                },
                "total": {
                    "format": "int64",
                    "type": "integer"
                }
            },
            "type": "object"
        },
        "PageDto«HermesBillImportInfoDto»": {
            "properties": {
                "pageNum": {
                    "format": "int64",
                    "type": "integer"
                },
                "pages": {
                    "format": "int64",
                    "type": "integer"
                },
                "records": {
                    "items": {
                        "$ref": "#/definitions/HermesBillImportInfoDto"
                    },
                    "type": "array"
                },
                "total": {
                    "format": "int64",
                    "type": "integer"
                }
            },
            "type": "object"
        },
        "PageDto«HermesBillResultDto»": {
            "properties": {
                "pageNum": {
                    "format": "int64",
                    "type": "integer"
                },
                "pages": {
                    "format": "int64",
                    "type": "integer"
                },
                "records": {
                    "items": {
                        "$ref": "#/definitions/HermesBillResultDto"
                    },
                    "type": "array"
                },
                "total": {
                    "format": "int64",
                    "type": "integer"
                }
            },
            "type": "object"
        },
        "PageDto«HermesBillSystemInfoDto»": {
            "properties": {
                "pageNum": {
                    "format": "int64",
                    "type": "integer"
                },
                "pages": {
                    "format": "int64",
                    "type": "integer"
                },
                "records": {
                    "items": {
                        "$ref": "#/definitions/HermesBillSystemInfoDto"
                    },
                    "type": "array"
                },
                "total": {
                    "format": "int64",
                    "type": "integer"
                }
            },
            "type": "object"
        },
        "PageDto«HermesSapBillInfo»": {
            "properties": {
                "pageNum": {
                    "format": "int64",
                    "type": "integer"
                },
                "pages": {
                    "format": "int64",
                    "type": "integer"
                },
                "records": {
                    "items": {
                        "$ref": "#/definitions/HermesSapBillInfo"
                    },
                    "type": "array"
                },
                "total": {
                    "format": "int64",
                    "type": "integer"
                }
            },
            "type": "object"
        },
        "SalesOrderCancelDto": {
            "description": "SalesOrder订单取消信息",
            "properties": {
                "cancelAmount": {
                    "description": "退款金额",
                    "format": "double",
                    "type": "number"
                },
                "cancelComments": {
                    "description": "备注",
                    "type": "string"
                },
                "cancelGoods": {
                    "description": "取消商品",
                    "type": "string"
                },
                "cancelReason": {
                    "description": "取消原因",
                    "type": "string"
                },
                "cancelStatus": {
                    "description": "当前状态",
                    "type": "string"
                },
                "cancelTime": {
                    "description": "发起时间",
                    "format": "date-time",
                    "type": "string"
                },
                "cancelTimes": {
                    "description": "取消次数",
                    "type": "string"
                },
                "cancelType": {
                    "description": "取消类型",
                    "type": "string"
                }
            },
            "type": "object"
        },
        "发货单信息": {
            "properties": {
                "amount": {
                    "description": "已支付总额",
                    "format": "double",
                    "type": "number"
                },
                "logisticsNumber": {
                    "description": "物流单号",
                    "type": "string"
                },
                "orderDefWareHouse": {
                    "description": "默认发货仓",
                    "type": "string"
                },
                "purchaseOrderNumber": {
                    "description": "SAP订单号",
                    "type": "string"
                },
                "shippingTime": {
                    "description": "发货时间",
                    "format": "date-time",
                    "type": "string"
                },
                "status": {
                    "description": "PO单状态",
                    "type": "string"
                }
            },
            "type": "object"
        },
        "对账结果详情": {
            "properties": {
                "assignmentDtoList": {
                    "description": "订单账单信息",
                    "items": {
                        "$ref": "#/definitions/HermesBillAssignmentDto"
                    },
                    "type": "array"
                },
                "billErrorDetail": {
                    "description": "异常详情",
                    "type": "string"
                },
                "billSystemInfoDtoList": {
                    "description": "订单账单信息",
                    "items": {
                        "$ref": "#/definitions/HermesBillSystemInfoDto"
                    },
                    "type": "array"
                },
                "channelId": {
                    "description": "订单渠道",
                    "type": "string"
                },
                "createOp": {
                    "description": "操作人",
                    "type": "string"
                },
                "eventTime": {
                    "description": "对账执行日期",
                    "format": "date-time",
                    "type": "string"
                },
                "orderPaymentDtoList": {
                    "description": "订单支付信息",
                    "items": {
                        "$ref": "#/definitions/订单支付信息"
                    },
                    "type": "array"
                },
                "orderTime": {
                    "description": "订单创建日期",
                    "format": "date-time",
                    "type": "string"
                },
                "purchaseOrderList": {
                    "description": "发货单信息",
                    "items": {
                        "$ref": "#/definitions/发货单信息"
                    },
                    "type": "array"
                },
                "salesOrderCancelDtoList": {
                    "description": "订单取消信息",
                    "items": {
                        "$ref": "#/definitions/SalesOrderCancelDto"
                    },
                    "type": "array"
                },
                "salesOrderNumber": {
                    "description": "订单号",
                    "type": "string"
                },
                "sapBillInfoDtoList": {
                    "description": "订单账单信息",
                    "items": {
                        "$ref": "#/definitions/HermesSapBillInfoDto"
                    },
                    "type": "array"
                },
                "status": {
                    "description": "当前状态",
                    "type": "string"
                },
                "updateTime": {
                    "description": "对账更新日期",
                    "format": "date-time",
                    "type": "string"
                }
            },
            "type": "object"
        },
        "订单支付信息": {
            "properties": {
                "paymentAmount": {
                    "description": "支付金额",
                    "format": "double",
                    "type": "number"
                },
                "paymentMethod": {
                    "description": "付款方式",
                    "type": "string"
                },
                "paymentNo": {
                    "description": "支付交易号",
                    "type": "string"
                },
                "paymentSerialId": {
                    "description": "付款编号",
                    "type": "string"
                },
                "paymentTime": {
                    "description": "付款时间",
                    "format": "date-time",
                    "type": "string"
                }
            },
            "type": "object"
        }
    },
    "host": "10.157.24.133:10023",
    "info": {
        "contact": {},
        "description": "服务接口文档",
        "license": {},
        "termsOfService": "https://www.sephora.cn",
        "title": "丝芙兰对账API文档",
        "version": "2.0"
    },
    "paths": {
        "/v1/finance/hermes/bill/assignment": {
            "put": {
                "consumes": [
                    "application/json"
                ],
                "description": "处理对账任务：复审、关闭",
                "operationId": "assignmentUsingPUT",
                "parameters": [
                    {
                        "description": "loginName",
                        "in": "header",
                        "name": "loginName",
                        "required": true,
                        "type": "string"
                    },
                    {
                        "description": "assignmentUpdateDto",
                        "in": "body",
                        "name": "assignmentUpdateDto",
                        "required": true,
                        "schema": {
                            "$ref": "#/definitions/HermesBillAssignmentUpdateDto"
                        }
                    }
                ],
                "produces": [
                    "*/*"
                ],
                "responses": {
                    "200": {
                        "description": "OK",
                        "schema": {
                            "$ref": "#/definitions/CommonResponse«boolean»"
                        }
                    },
                    "201": {
                        "description": "Created"
                    },
                    "401": {
                        "description": "Unauthorized"
                    },
                    "403": {
                        "description": "Forbidden"
                    },
                    "404": {
                        "description": "Not Found"
                    }
                },
                "summary": "对账任务处理",
                "tags": [
                    "hermes-assignment-management-controller"
                ]
            }
        },
        "/v1/finance/hermes/bill/assignments": {
            "post": {
                "consumes": [
                    "application/json"
                ],
                "description": "对账任务列表分页显示",
                "operationId": "assignmentsUsingPOST",
                "parameters": [
                    {
                        "description": "assignmentQueryDto",
                        "in": "body",
                        "name": "assignmentQueryDto",
                        "required": false,
                        "schema": {
                            "$ref": "#/definitions/HermesBillAssignmentQueryDto"
                        }
                    }
                ],
                "produces": [
                    "*/*"
                ],
                "responses": {
                    "200": {
                        "description": "OK",
                        "schema": {
                            "$ref": "#/definitions/CommonResponse«PageDto«HermesBillAssignmentDto»»"
                        }
                    },
                    "201": {
                        "description": "Created"
                    },
                    "401": {
                        "description": "Unauthorized"
                    },
                    "403": {
                        "description": "Forbidden"
                    },
                    "404": {
                        "description": "Not Found"
                    }
                },
                "summary": "对账任务列表",
                "tags": [
                    "hermes-assignment-management-controller"
                ]
            }
        },
        "/v1/finance/hermes/bill/exception": {
            "put": {
                "consumes": [
                    "application/json"
                ],
                "description": "对账异常处理：交由下一节点人处理、忽略、重新校验",
                "operationId": "exceptionUsingPUT",
                "parameters": [
                    {
                        "description": "loginName",
                        "in": "header",
                        "name": "loginName",
                        "required": true,
                        "type": "string"
                    },
                    {
                        "description": "exceptionUpdateDto",
                        "in": "body",
                        "name": "exceptionUpdateDto",
                        "required": true,
                        "schema": {
                            "$ref": "#/definitions/HermesExceptionUpdateDto"
                        }
                    }
                ],
                "produces": [
                    "*/*"
                ],
                "responses": {
                    "200": {
                        "description": "OK",
                        "schema": {
                            "$ref": "#/definitions/CommonResponse«boolean»"
                        }
                    },
                    "201": {
                        "description": "Created"
                    },
                    "401": {
                        "description": "Unauthorized"
                    },
                    "403": {
                        "description": "Forbidden"
                    },
                    "404": {
                        "description": "Not Found"
                    }
                },
                "summary": " 对账异常处理",
                "tags": [
                    "hermes-assignment-management-controller"
                ]
            }
        },
        "/v1/finance/hermes/bill/import/detail/{hermesBillImportInfoSysId}": {
            "get": {
                "consumes": [
                    "application/json"
                ],
                "description": "对账日志详情接口",
                "operationId": "getHermesBillImportDetailInfoUsingGET",
                "parameters": [
                    {
                        "description": "导入账单信息主键",
                        "format": "int64",
                        "in": "path",
                        "name": "hermesBillImportInfoSysId",
                        "required": true,
                        "type": "integer"
                    }
                ],
                "produces": [
                    "*/*"
                ],
                "responses": {
                    "200": {
                        "description": "OK",
                        "schema": {
                            "$ref": "#/definitions/CommonResponse«HermesBillImportDetailInfoDto»"
                        }
                    },
                    "401": {
                        "description": "Unauthorized"
                    },
                    "403": {
                        "description": "Forbidden"
                    },
                    "404": {
                        "description": "Not Found"
                    }
                },
                "summary": "对账日志详情接口",
                "tags": [
                    "hermes-bill-management-controller"
                ]
            }
        },
        "/v1/finance/hermes/bill/import/list": {
            "post": {
                "consumes": [
                    "application/json"
                ],
                "description": "对账日志列表分页接口",
                "operationId": "getHermesBillImportInfoUsingPOST",
                "parameters": [
                    {
                        "description": "hermesBillImportInfoQueryDto",
                        "in": "body",
                        "name": "hermesBillImportInfoQueryDto",
                        "required": true,
                        "schema": {
                            "$ref": "#/definitions/HermesBillImportInfoQueryDto"
                        }
                    }
                ],
                "produces": [
                    "*/*"
                ],
                "responses": {
                    "200": {
                        "description": "OK",
                        "schema": {
                            "$ref": "#/definitions/CommonResponse«PageDto«HermesBillImportInfoDto»»"
                        }
                    },
                    "201": {
                        "description": "Created"
                    },
                    "401": {
                        "description": "Unauthorized"
                    },
                    "403": {
                        "description": "Forbidden"
                    },
                    "404": {
                        "description": "Not Found"
                    }
                },
                "summary": "对账日志接口",
                "tags": [
                    "hermes-bill-management-controller"
                ]
            }
        },
        "/v1/finance/hermes/bill/list": {
            "post": {
                "consumes": [
                    "application/json"
                ],
                "description": "账单管理列表分页接口",
                "operationId": "getHermesBillSystemInfoUsingPOST",
                "parameters": [
                    {
                        "description": "hermesBillSystemInfoQueryDto",
                        "in": "body",
                        "name": "hermesBillSystemInfoQueryDto",
                        "required": true,
                        "schema": {
                            "$ref": "#/definitions/HermesBillSystemInfoQueryDto"
                        }
                    }
                ],
                "produces": [
                    "*/*"
                ],
                "responses": {
                    "200": {
                        "description": "OK",
                        "schema": {
                            "$ref": "#/definitions/CommonResponse«PageDto«HermesBillSystemInfoDto»»"
                        }
                    },
                    "201": {
                        "description": "Created"
                    },
                    "401": {
                        "description": "Unauthorized"
                    },
                    "403": {
                        "description": "Forbidden"
                    },
                    "404": {
                        "description": "Not Found"
                    }
                },
                "summary": "账单管理接口",
                "tags": [
                    "hermes-bill-management-controller"
                ]
            }
        },
        "/v1/finance/hermes/bill/location/{transactionNumber}": {
            "get": {
                "consumes": [
                    "application/json"
                ],
                "description": "交易流水号定位接口",
                "operationId": "locationTransactionNumberUsingGET",
                "parameters": [
                    {
                        "description": "交易流水号",
                        "in": "path",
                        "name": "transactionNumber",
                        "required": true,
                        "type": "string"
                    }
                ],
                "produces": [
                    "*/*"
                ],
                "responses": {
                    "200": {
                        "description": "OK",
                        "schema": {
                            "$ref": "#/definitions/CommonResponse«HermesBillTransactionNumberDto»"
                        }
                    },
                    "401": {
                        "description": "Unauthorized"
                    },
                    "403": {
                        "description": "Forbidden"
                    },
                    "404": {
                        "description": "Not Found"
                    }
                },
                "summary": "交易流水号定位接口",
                "tags": [
                    "hermes-bill-management-controller"
                ]
            }
        },
        "/v1/finance/hermes/bill/memory": {
            "post": {
                "consumes": [
                    "application/json"
                ],
                "description": "手动添加账单接口",
                "operationId": "createHermesBillSystemInfoUsingPOST",
                "parameters": [
                    {
                        "description": "hermesBillSystemInfoDto",
                        "in": "body",
                        "name": "hermesBillSystemInfoDto",
                        "required": true,
                        "schema": {
                            "$ref": "#/definitions/HermesBillSystemInfoDto"
                        }
                    }
                ],
                "produces": [
                    "*/*"
                ],
                "responses": {
                    "200": {
                        "description": "OK",
                        "schema": {
                            "$ref": "#/definitions/CommonResponse«boolean»"
                        }
                    },
                    "201": {
                        "description": "Created"
                    },
                    "401": {
                        "description": "Unauthorized"
                    },
                    "403": {
                        "description": "Forbidden"
                    },
                    "404": {
                        "description": "Not Found"
                    }
                },
                "summary": "手动添加账单接口",
                "tags": [
                    "hermes-bill-management-controller"
                ]
            }
        },
        "/v1/finance/hermes/bill/reconciliation": {
            "get": {
                "consumes": [
                    "application/json"
                ],
                "description": "调用对账",
                "operationId": "reconciliationUsingGET",
                "parameters": [
                    {
                        "description": "salesOrderNumber",
                        "in": "query",
                        "name": "salesOrderNumber",
                        "required": false,
                        "type": "string"
                    }
                ],
                "produces": [
                    "*/*"
                ],
                "responses": {
                    "200": {
                        "description": "OK"
                    },
                    "401": {
                        "description": "Unauthorized"
                    },
                    "403": {
                        "description": "Forbidden"
                    },
                    "404": {
                        "description": "Not Found"
                    }
                },
                "summary": "调用对账",
                "tags": [
                    "hermes-bill-management-controller"
                ]
            }
        },
        "/v1/finance/hermes/bill/result": {
            "get": {
                "consumes": [
                    "application/json"
                ],
                "description": "对账结果详情",
                "operationId": "resultDetailUsingGET",
                "parameters": [
                    {
                        "description": "对账结果主键",
                        "format": "int64",
                        "in": "query",
                        "name": "billResultId",
                        "required": false,
                        "type": "integer"
                    }
                ],
                "produces": [
                    "*/*"
                ],
                "responses": {
                    "200": {
                        "description": "OK",
                        "schema": {
                            "$ref": "#/definitions/CommonResponse«对账结果详情»"
                        }
                    },
                    "401": {
                        "description": "Unauthorized"
                    },
                    "403": {
                        "description": "Forbidden"
                    },
                    "404": {
                        "description": "Not Found"
                    }
                },
                "summary": " 对账结果详情",
                "tags": [
                    "hermes-result-management-controller"
                ]
            }
        },
        "/v1/finance/hermes/bill/results": {
            "post": {
                "consumes": [
                    "application/json"
                ],
                "description": "对账结果查询列表分页显示",
                "operationId": "resultsUsingPOST",
                "parameters": [
                    {
                        "description": "hermesResultQueryDto",
                        "in": "body",
                        "name": "hermesResultQueryDto",
                        "required": false,
                        "schema": {
                            "$ref": "#/definitions/HermesResultQueryDto"
                        }
                    }
                ],
                "produces": [
                    "*/*"
                ],
                "responses": {
                    "200": {
                        "description": "OK",
                        "schema": {
                            "$ref": "#/definitions/CommonResponse«PageDto«HermesBillResultDto»»"
                        }
                    },
                    "201": {
                        "description": "Created"
                    },
                    "401": {
                        "description": "Unauthorized"
                    },
                    "403": {
                        "description": "Forbidden"
                    },
                    "404": {
                        "description": "Not Found"
                    }
                },
                "summary": " 对账结果列表",
                "tags": [
                    "hermes-result-management-controller"
                ]
            }
        },
        "/v1/finance/hermes/bill/sap/list": {
            "post": {
                "consumes": [
                    "application/json"
                ],
                "description": "SAP账单查询接口",
                "operationId": "queryHermesBillListUsingPOST",
                "parameters": [
                    {
                        "description": "hermesSapBillInfoQueryDto",
                        "in": "body",
                        "name": "hermesSapBillInfoQueryDto",
                        "required": true,
                        "schema": {
                            "$ref": "#/definitions/HermesSapBillInfoQueryDto"
                        }
                    }
                ],
                "produces": [
                    "*/*"
                ],
                "responses": {
                    "200": {
                        "description": "OK",
                        "schema": {
                            "$ref": "#/definitions/CommonResponse«PageDto«HermesSapBillInfo»»"
                        }
                    },
                    "201": {
                        "description": "Created"
                    },
                    "401": {
                        "description": "Unauthorized"
                    },
                    "403": {
                        "description": "Forbidden"
                    },
                    "404": {
                        "description": "Not Found"
                    }
                },
                "summary": "SAP账单查询接口",
                "tags": [
                    "hermes-bill-management-controller"
                ]
            }
        },
        "/v1/finance/hermes/bill/sap/upload": {
            "post": {
                "consumes": [
                    "multipart/form-data"
                ],
                "description": "SAP账单导入接口",
                "operationId": "uploadSapBillUsingPOST",
                "parameters": [
                    {
                        "description": "multipartFile",
                        "in": "formData",
                        "name": "multipartFile",
                        "required": true,
                        "type": "file"
                    }
                ],
                "produces": [
                    "*/*"
                ],
                "responses": {
                    "200": {
                        "description": "OK",
                        "schema": {
                            "$ref": "#/definitions/CommonResponse«boolean»"
                        }
                    },
                    "201": {
                        "description": "Created"
                    },
                    "401": {
                        "description": "Unauthorized"
                    },
                    "403": {
                        "description": "Forbidden"
                    },
                    "404": {
                        "description": "Not Found"
                    }
                },
                "summary": "SAP账单导入接口",
                "tags": [
                    "hermes-bill-management-controller"
                ]
            }
        },
        "/v1/finance/hermes/bill/upload": {
            "post": {
                "consumes": [
                    "multipart/form-data"
                ],
                "description": "账单管理导入接口",
                "operationId": "uploadHermesBillUsingPOST",
                "parameters": [
                    {
                        "description": "upload",
                        "in": "formData",
                        "name": "upload",
                        "required": true,
                        "type": "file"
                    },
                    {
                        "description": "SF/EMS/SILK/JD/WX/ALI",
                        "in": "query",
                        "name": "type",
                        "required": false,
                        "type": "string"
                    }
                ],
                "produces": [
                    "*/*"
                ],
                "responses": {
                    "200": {
                        "description": "OK",
                        "schema": {
                            "$ref": "#/definitions/CommonResponse«boolean»"
                        }
                    },
                    "201": {
                        "description": "Created"
                    },
                    "401": {
                        "description": "Unauthorized"
                    },
                    "403": {
                        "description": "Forbidden"
                    },
                    "404": {
                        "description": "Not Found"
                    }
                },
                "summary": "账单管理导入接口",
                "tags": [
                    "hermes-bill-management-controller"
                ]
            }
        }
    },
    "swagger": "2.0",
    "tags": [
        {
            "description": "Hermes Result Management Controller",
            "name": "hermes-result-management-controller"
        },
        {
            "description": "Hermes Assignment Management Controller",
            "name": "hermes-assignment-management-controller"
        },
        {
            "description": "Hermes Bill Management Controller",
            "name": "hermes-bill-management-controller"
        }
    ]
}