{
    "basePath": "/",
    "definitions": {
        "CardBenefitsInfoDTO": {
            "properties": {
                "cardLevel": {
                    "description": "会员卡等级",
                    "type": "string"
                },
                "cardNo": {
                    "description": "会员卡号",
                    "type": "string"
                },
                "effectiveTime": {
                    "format": "date-time",
                    "type": "string"
                },
                "fullYearTime": {
                    "description": "会员卡满一年的时间",
                    "format": "date-time",
                    "type": "string"
                },
                "registerTime": {
                    "description": "会员卡注册时间",
                    "format": "date-time",
                    "type": "string"
                },
                "remainingPoints": {
                    "description": "享受福利所剩余的积分",
                    "format": "double",
                    "type": "number"
                },
                "remainingPurchaseTimes": {
                    "description": "享受福利所剩余的购物次数",
                    "format": "int32",
                    "type": "integer"
                }
            },
            "type": "object"
        },
        "CommonResponse«double»": {
            "properties": {
                "errorCode": {
                    "description": "错误代码",
                    "format": "int32",
                    "type": "integer"
                },
                "errorMessage": {
                    "description": "错误描述信息",
                    "type": "string"
                },
                "results": {
                    "description": "返回结果",
                    "format": "double",
                    "type": "number"
                },
                "status": {
                    "description": "处理状态： 0 正常状态或业务异常，1 系统异常",
                    "format": "int64",
                    "type": "integer"
                },
                "timeStamp": {
                    "description": "服务端返回请求结果的时间",
                    "format": "int64",
                    "type": "integer"
                }
            },
            "required": [
                "status",
                "timeStamp"
            ],
            "type": "object"
        },
        "CommonResponse«string»": {
            "properties": {
                "errorCode": {
                    "description": "错误代码",
                    "format": "int32",
                    "type": "integer"
                },
                "errorMessage": {
                    "description": "错误描述信息",
                    "type": "string"
                },
                "results": {
                    "description": "返回结果",
                    "type": "string"
                },
                "status": {
                    "description": "处理状态： 0 正常状态或业务异常，1 系统异常",
                    "format": "int64",
                    "type": "integer"
                },
                "timeStamp": {
                    "description": "服务端返回请求结果的时间",
                    "format": "int64",
                    "type": "integer"
                }
            },
            "required": [
                "status",
                "timeStamp"
            ],
            "type": "object"
        },
        "ExchangeCardDTO": {
            "properties": {
                "channel": {
                    "description": "换卡渠道",
                    "type": "string"
                },
                "email": {
                    "description": "邮箱",
                    "type": "string"
                },
                "mobile": {
                    "description": "手机号",
                    "type": "string"
                },
                "operateTime": {
                    "description": "操作的时间",
                    "format": "date-time",
                    "type": "string"
                },
                "originalCardNo": {
                    "description": "换卡之前的卡号",
                    "type": "string"
                },
                "targetCardNo": {
                    "description": "更换卡的卡号",
                    "type": "string"
                }
            },
            "type": "object"
        },
        "ImportUserBeautyKolTagDTO": {
            "properties": {
                "cardNo": {
                    "description": "申请用户手机号对应的会员卡",
                    "type": "string"
                },
                "mobile": {
                    "description": "申请用户的手机号",
                    "type": "string"
                },
                "requestTime": {
                    "description": "用户申请的时间",
                    "format": "date-time",
                    "type": "string"
                },
                "resultCardNo": {
                    "description": "通过手机号筛选过后的会员卡号，用于注册使用，前端不需要传参",
                    "type": "string"
                }
            },
            "required": [
                "cardNo",
                "mobile",
                "requestTime"
            ],
            "type": "object"
        },
        "RegisterNewPinkCardDTO": {
            "properties": {
                "channel": {
                    "description": "注册粉卡的渠道",
                    "type": "string"
                },
                "mobile": {
                    "description": "注册粉卡时手机号",
                    "type": "string"
                },
                "storeCode": {
                    "description": "注册粉卡的门店",
                    "type": "string"
                }
            },
            "type": "object"
        },
        "UpdateCardLevelDTO": {
            "properties": {
                "cardNo": {
                    "type": "string"
                },
                "fromLevel": {
                    "type": "string"
                },
                "toLevel": {
                    "type": "string"
                },
                "updateTime": {
                    "format": "date-time",
                    "type": "string"
                }
            },
            "type": "object"
        },
        "WechatMiniUserRegisterInfoDTO": {
            "properties": {
                "bindMobileTime": {
                    "description": "小程序绑定手机号的时间",
                    "type": "string"
                },
                "cardNo": {
                    "description": "注册小程序的手机号绑定的会员卡",
                    "type": "string"
                },
                "mobile": {
                    "description": "注册小程序的手机号",
                    "type": "string"
                },
                "openId": {
                    "description": "小程序的openId",
                    "type": "string"
                },
                "registerChannel": {
                    "description": "小程序渠道",
                    "type": "string"
                },
                "registerStoreCode": {
                    "description": "注册小程序的门店号",
                    "type": "string"
                },
                "registerTime": {
                    "description": "注册小程序的时间",
                    "type": "string"
                },
                "unionId": {
                    "description": "小程序的unionId",
                    "type": "string"
                }
            },
            "type": "object"
        },
        "初始化EB粉卡DTO": {
            "properties": {
                "cardNo": {
                    "description": "会员卡对应的卡号",
                    "type": "string"
                },
                "channel": {
                    "description": "粉卡发放渠道",
                    "type": "string"
                },
                "email": {
                    "description": "会员卡对应的邮箱",
                    "type": "string"
                },
                "mobile": {
                    "description": "会员卡对应的手机号",
                    "type": "string"
                },
                "registerTime": {
                    "description": "会员",
                    "format": "date-time",
                    "type": "string"
                },
                "source": {
                    "description": "会员卡注册的渠道",
                    "type": "string"
                },
                "storeId": {
                    "description": "会员卡注册的门店",
                    "type": "string"
                }
            },
            "type": "object"
        },
        "绑卡": {
            "properties": {
                "cardNo": {
                    "description": "会员卡对应的卡号",
                    "type": "string"
                },
                "email": {
                    "description": "会员卡对应的邮箱",
                    "type": "string"
                },
                "mobile": {
                    "description": "会员卡对应的手机号",
                    "type": "string"
                }
            },
            "type": "object"
        },
        "绑定CRM的粉卡": {
            "properties": {
                "cardNo": {
                    "description": "会员卡对应的卡号",
                    "type": "string"
                },
                "channel": {
                    "description": "粉卡发放渠道",
                    "type": "string"
                },
                "email": {
                    "description": "会员卡对应的邮箱",
                    "type": "string"
                },
                "mobile": {
                    "description": "会员卡对应的手机号",
                    "type": "string"
                },
                "registerTime": {
                    "description": "会员",
                    "format": "date-time",
                    "type": "string"
                },
                "source": {
                    "description": "会员卡注册的渠道",
                    "type": "string"
                },
                "storeId": {
                    "description": "会员卡注册的门店",
                    "type": "string"
                }
            },
            "type": "object"
        }
    },
    "host": "10.157.24.138:10021",
    "info": {
        "contact": {},
        "description": "服务接口文档",
        "license": {},
        "termsOfService": "https://www.sephora.cn",
        "title": "丝芙兰全渠道CRM数据中枢API文档",
        "version": "2.0"
    },
    "paths": {
        "/v1/omni/crm/hub/beauty/kol": {
            "post": {
                "consumes": [
                    "application/json"
                ],
                "description": "接收用户BeautyKol的申请，记录日志并通知Myaccount",
                "operationId": "importUserBeautyKolTagUsingPOST",
                "parameters": [
                    {
                        "description": "当前登陆用户系统编号",
                        "in": "header",
                        "name": "uid",
                        "required": false,
                        "type": "string"
                    },
                    {
                        "description": "importUserBeautyKolTagDTO",
                        "in": "body",
                        "name": "importUserBeautyKolTagDTO",
                        "required": true,
                        "schema": {
                            "$ref": "#/definitions/ImportUserBeautyKolTagDTO"
                        }
                    }
                ],
                "produces": [
                    "*/*"
                ],
                "responses": {
                    "200": {
                        "description": "OK",
                        "schema": {
                            "$ref": "#/definitions/CommonResponse«string»"
                        }
                    },
                    "201": {
                        "description": "Created"
                    },
                    "401": {
                        "description": "Unauthorized"
                    },
                    "403": {
                        "description": "Forbidden"
                    },
                    "404": {
                        "description": "Not Found"
                    }
                },
                "summary": "接收CRM推送的用户申请BeautyKol的数据",
                "tags": [
                    "beauty-kol-controller"
                ]
            }
        },
        "/v1/omni/crm/hub/cache/all/mobile/default/card": {
            "delete": {
                "consumes": [
                    "application/json"
                ],
                "description": "慎重，请在相关专业人士的指导下操作",
                "operationId": "removeAllMobileCardCacheUsingDELETE",
                "parameters": [
                    {
                        "description": "当前登陆用户系统编号",
                        "in": "header",
                        "name": "uid",
                        "required": false,
                        "type": "string"
                    },
                    {
                        "description": "token",
                        "in": "query",
                        "name": "token",
                        "required": true,
                        "type": "string"
                    }
                ],
                "produces": [
                    "*/*"
                ],
                "responses": {
                    "200": {
                        "description": "OK",
                        "schema": {
                            "$ref": "#/definitions/CommonResponse«string»"
                        }
                    },
                    "204": {
                        "description": "No Content"
                    },
                    "401": {
                        "description": "Unauthorized"
                    },
                    "403": {
                        "description": "Forbidden"
                    }
                },
                "summary": "清理全部手机号对应会员卡的缓存",
                "tags": [
                    "cache-manager-controller"
                ]
            }
        },
        "/v1/omni/crm/hub/cache/card/info": {
            "delete": {
                "consumes": [
                    "application/json"
                ],
                "operationId": "removeCardInfoCacheUsingDELETE",
                "parameters": [
                    {
                        "description": "当前登陆用户系统编号",
                        "in": "header",
                        "name": "uid",
                        "required": false,
                        "type": "string"
                    },
                    {
                        "description": "cardNo",
                        "in": "query",
                        "name": "cardNo",
                        "required": true,
                        "type": "string"
                    }
                ],
                "produces": [
                    "*/*"
                ],
                "responses": {
                    "200": {
                        "description": "OK",
                        "schema": {
                            "$ref": "#/definitions/CommonResponse«string»"
                        }
                    },
                    "204": {
                        "description": "No Content"
                    },
                    "401": {
                        "description": "Unauthorized"
                    },
                    "403": {
                        "description": "Forbidden"
                    }
                },
                "summary": "removeCardInfoCache",
                "tags": [
                    "cache-manager-controller"
                ]
            }
        },
        "/v1/omni/crm/hub/cache/mobile/default/card": {
            "delete": {
                "consumes": [
                    "application/json"
                ],
                "operationId": "removeMobileDefaultCardCacheUsingDELETE",
                "parameters": [
                    {
                        "description": "当前登陆用户系统编号",
                        "in": "header",
                        "name": "uid",
                        "required": false,
                        "type": "string"
                    },
                    {
                        "description": "mobile",
                        "in": "query",
                        "name": "mobile",
                        "required": true,
                        "type": "string"
                    }
                ],
                "produces": [
                    "*/*"
                ],
                "responses": {
                    "200": {
                        "description": "OK",
                        "schema": {
                            "$ref": "#/definitions/CommonResponse«string»"
                        }
                    },
                    "204": {
                        "description": "No Content"
                    },
                    "401": {
                        "description": "Unauthorized"
                    },
                    "403": {
                        "description": "Forbidden"
                    }
                },
                "summary": "清除手机号对应的默认会员卡信息的缓存",
                "tags": [
                    "cache-manager-controller"
                ]
            }
        },
        "/v1/omni/crm/hub/card/benefits/info": {
            "post": {
                "consumes": [
                    "application/json"
                ],
                "operationId": "updateCardBenefitsInfoUsingPOST",
                "parameters": [
                    {
                        "description": "当前登陆用户系统编号",
                        "in": "header",
                        "name": "uid",
                        "required": false,
                        "type": "string"
                    },
                    {
                        "description": "cardBenefitsInfoDTO",
                        "in": "body",
                        "name": "cardBenefitsInfoDTO",
                        "required": true,
                        "schema": {
                            "$ref": "#/definitions/CardBenefitsInfoDTO"
                        }
                    }
                ],
                "produces": [
                    "*/*"
                ],
                "responses": {
                    "200": {
                        "description": "OK",
                        "schema": {
                            "$ref": "#/definitions/CommonResponse«string»"
                        }
                    },
                    "201": {
                        "description": "Created"
                    },
                    "401": {
                        "description": "Unauthorized"
                    },
                    "403": {
                        "description": "Forbidden"
                    },
                    "404": {
                        "description": "Not Found"
                    }
                },
                "summary": "updateCardBenefitsInfo",
                "tags": [
                    "card-controller"
                ]
            }
        },
        "/v1/omni/crm/hub/card/level": {
            "put": {
                "consumes": [
                    "application/json"
                ],
                "operationId": "updateCardLevelUsingPUT",
                "parameters": [
                    {
                        "description": "当前登陆用户系统编号",
                        "in": "header",
                        "name": "uid",
                        "required": false,
                        "type": "string"
                    },
                    {
                        "description": "updateCardLevelDTO",
                        "in": "body",
                        "name": "updateCardLevelDTO",
                        "required": true,
                        "schema": {
                            "$ref": "#/definitions/UpdateCardLevelDTO"
                        }
                    }
                ],
                "produces": [
                    "*/*"
                ],
                "responses": {
                    "200": {
                        "description": "OK",
                        "schema": {
                            "$ref": "#/definitions/CommonResponse«string»"
                        }
                    },
                    "201": {
                        "description": "Created"
                    },
                    "401": {
                        "description": "Unauthorized"
                    },
                    "403": {
                        "description": "Forbidden"
                    },
                    "404": {
                        "description": "Not Found"
                    }
                },
                "summary": "updateCardLevel",
                "tags": [
                    "card-controller"
                ]
            }
        },
        "/v1/omni/crm/hub/feign/binding/card": {
            "post": {
                "consumes": [
                    "application/json"
                ],
                "description": "EB在注册时绑定了会员卡，CRM-HUB需要设置手机号对应的默认卡信息",
                "operationId": "bindCardUsingPOST",
                "parameters": [
                    {
                        "description": "当前登陆用户系统编号",
                        "in": "header",
                        "name": "uid",
                        "required": false,
                        "type": "string"
                    },
                    {
                        "description": "bindCardDTO",
                        "in": "body",
                        "name": "bindCardDTO",
                        "required": true,
                        "schema": {
                            "$ref": "#/definitions/绑卡"
                        }
                    }
                ],
                "produces": [
                    "*/*"
                ],
                "responses": {
                    "200": {
                        "description": "OK",
                        "schema": {
                            "$ref": "#/definitions/CommonResponse«string»"
                        }
                    },
                    "201": {
                        "description": "Created"
                    },
                    "401": {
                        "description": "Unauthorized"
                    },
                    "403": {
                        "description": "Forbidden"
                    },
                    "404": {
                        "description": "Not Found"
                    }
                },
                "summary": "EB绑定会员卡",
                "tags": [
                    "feign-controller"
                ]
            }
        },
        "/v1/omni/crm/hub/feign/card/benefits/description": {
            "get": {
                "consumes": [
                    "application/json"
                ],
                "operationId": "getCardBenefitsDescriptionUsingGET",
                "parameters": [
                    {
                        "description": "当前登陆用户系统编号",
                        "in": "header",
                        "name": "uid",
                        "required": false,
                        "type": "string"
                    },
                    {
                        "description": "cardNo",
                        "in": "query",
                        "name": "cardNo",
                        "required": true,
                        "type": "string"
                    }
                ],
                "produces": [
                    "*/*"
                ],
                "responses": {
                    "200": {
                        "description": "OK",
                        "schema": {
                            "$ref": "#/definitions/CommonResponse«string»"
                        }
                    },
                    "401": {
                        "description": "Unauthorized"
                    },
                    "403": {
                        "description": "Forbidden"
                    },
                    "404": {
                        "description": "Not Found"
                    }
                },
                "summary": "获取会员卡权益信息",
                "tags": [
                    "feign-controller"
                ]
            }
        },
        "/v1/omni/crm/hub/feign/card/benefits/process": {
            "get": {
                "consumes": [
                    "application/json"
                ],
                "operationId": "getCardBenefitsProcessUsingGET",
                "parameters": [
                    {
                        "description": "当前登陆用户系统编号",
                        "in": "header",
                        "name": "uid",
                        "required": false,
                        "type": "string"
                    },
                    {
                        "description": "cardNo",
                        "in": "query",
                        "name": "cardNo",
                        "required": true,
                        "type": "string"
                    }
                ],
                "produces": [
                    "*/*"
                ],
                "responses": {
                    "200": {
                        "description": "OK",
                        "schema": {
                            "$ref": "#/definitions/CommonResponse«double»"
                        }
                    },
                    "401": {
                        "description": "Unauthorized"
                    },
                    "403": {
                        "description": "Forbidden"
                    },
                    "404": {
                        "description": "Not Found"
                    }
                },
                "summary": "获取会员卡升级进度",
                "tags": [
                    "feign-controller"
                ]
            }
        },
        "/v1/omni/crm/hub/feign/crm/pink/card": {
            "post": {
                "consumes": [
                    "application/json"
                ],
                "description": "手机号对应的默认卡设置",
                "operationId": "bindCrmPinkCardUsingPOST",
                "parameters": [
                    {
                        "description": "当前登陆用户系统编号",
                        "in": "header",
                        "name": "uid",
                        "required": false,
                        "type": "string"
                    },
                    {
                        "description": "bindCrmPinkCardDTO",
                        "in": "body",
                        "name": "bindCrmPinkCardDTO",
                        "required": true,
                        "schema": {
                            "$ref": "#/definitions/绑定CRM的粉卡"
                        }
                    }
                ],
                "produces": [
                    "*/*"
                ],
                "responses": {
                    "200": {
                        "description": "OK",
                        "schema": {
                            "$ref": "#/definitions/CommonResponse«string»"
                        }
                    },
                    "201": {
                        "description": "Created"
                    },
                    "401": {
                        "description": "Unauthorized"
                    },
                    "403": {
                        "description": "Forbidden"
                    },
                    "404": {
                        "description": "Not Found"
                    }
                },
                "summary": "CRM发放粉卡需通知到CRM-HUB",
                "tags": [
                    "feign-controller"
                ]
            }
        },
        "/v1/omni/crm/hub/feign/eb/pink/card": {
            "post": {
                "consumes": [
                    "application/json"
                ],
                "description": "粉卡数据初始化，默认卡的设置及推送卡信息至CRM",
                "operationId": "initEbPinkCardUsingPOST",
                "parameters": [
                    {
                        "description": "当前登陆用户系统编号",
                        "in": "header",
                        "name": "uid",
                        "required": false,
                        "type": "string"
                    },
                    {
                        "description": "initEbPinkCardDTO",
                        "in": "body",
                        "name": "initEbPinkCardDTO",
                        "required": true,
                        "schema": {
                            "$ref": "#/definitions/初始化EB粉卡DTO"
                        }
                    }
                ],
                "produces": [
                    "*/*"
                ],
                "responses": {
                    "200": {
                        "description": "OK",
                        "schema": {
                            "$ref": "#/definitions/CommonResponse«string»"
                        }
                    },
                    "201": {
                        "description": "Created"
                    },
                    "401": {
                        "description": "Unauthorized"
                    },
                    "403": {
                        "description": "Forbidden"
                    },
                    "404": {
                        "description": "Not Found"
                    }
                },
                "summary": "EB发放粉卡通知到CRM-HUB",
                "tags": [
                    "feign-controller"
                ]
            }
        },
        "/v1/omni/crm/hub/feign/exchange/card": {
            "put": {
                "consumes": [
                    "application/json"
                ],
                "description": "记录换卡流水，更改手机号对应的默认卡信息，删除会员卡对应的之前会员卡信息",
                "operationId": "exchangeCardUsingPUT",
                "parameters": [
                    {
                        "description": "当前登陆用户系统编号",
                        "in": "header",
                        "name": "uid",
                        "required": false,
                        "type": "string"
                    },
                    {
                        "description": "exchangeCardDTO",
                        "in": "body",
                        "name": "exchangeCardDTO",
                        "required": true,
                        "schema": {
                            "$ref": "#/definitions/ExchangeCardDTO"
                        }
                    }
                ],
                "produces": [
                    "*/*"
                ],
                "responses": {
                    "200": {
                        "description": "OK",
                        "schema": {
                            "$ref": "#/definitions/CommonResponse«string»"
                        }
                    },
                    "201": {
                        "description": "Created"
                    },
                    "401": {
                        "description": "Unauthorized"
                    },
                    "403": {
                        "description": "Forbidden"
                    },
                    "404": {
                        "description": "Not Found"
                    }
                },
                "summary": "EB换卡需通知CRM-HUB进行手机号默认卡的更换",
                "tags": [
                    "feign-controller"
                ]
            }
        },
        "/v1/omni/crm/hub/feign/exchange/cards": {
            "get": {
                "consumes": [
                    "application/json"
                ],
                "description": "根据手机号或邮箱获取会员卡列表，两者至少填写一个",
                "operationId": "getExchangeCardListByParamUsingGET",
                "parameters": [
                    {
                        "description": "当前登陆用户系统编号",
                        "in": "header",
                        "name": "uid",
                        "required": false,
                        "type": "string"
                    },
                    {
                        "description": "mobile",
                        "in": "query",
                        "name": "mobile",
                        "required": false,
                        "type": "string"
                    },
                    {
                        "description": "email",
                        "in": "query",
                        "name": "email",
                        "required": false,
                        "type": "string"
                    }
                ],
                "produces": [
                    "*/*"
                ],
                "responses": {
                    "200": {
                        "description": "OK",
                        "schema": {
                            "$ref": "#/definitions/CommonResponse«string»"
                        }
                    },
                    "401": {
                        "description": "Unauthorized"
                    },
                    "403": {
                        "description": "Forbidden"
                    },
                    "404": {
                        "description": "Not Found"
                    }
                },
                "summary": "获取可更换的会员卡列表信息",
                "tags": [
                    "feign-controller"
                ]
            }
        },
        "/v1/omni/crm/hub/feign/myaccount/default/card": {
            "get": {
                "consumes": [
                    "application/json"
                ],
                "operationId": "getDefaultCardByParamsUsingGET",
                "parameters": [
                    {
                        "description": "当前登陆用户系统编号",
                        "in": "header",
                        "name": "uid",
                        "required": false,
                        "type": "string"
                    },
                    {
                        "description": "mobile",
                        "in": "query",
                        "name": "mobile",
                        "required": false,
                        "type": "string"
                    },
                    {
                        "description": "email",
                        "in": "query",
                        "name": "email",
                        "required": false,
                        "type": "string"
                    },
                    {
                        "description": "channel",
                        "in": "query",
                        "name": "channel",
                        "required": true,
                        "type": "string"
                    }
                ],
                "produces": [
                    "*/*"
                ],
                "responses": {
                    "200": {
                        "description": "OK",
                        "schema": {
                            "$ref": "#/definitions/CommonResponse«string»"
                        }
                    },
                    "401": {
                        "description": "Unauthorized"
                    },
                    "403": {
                        "description": "Forbidden"
                    },
                    "404": {
                        "description": "Not Found"
                    }
                },
                "summary": "getDefaultCardByParams",
                "tags": [
                    "myaccount-portal-feign-controller"
                ]
            }
        },
        "/v1/omni/crm/hub/feign/myaccount/default/card/third": {
            "get": {
                "consumes": [
                    "application/json"
                ],
                "operationId": "getDefaultCardByThirdUnionIdUsingGET",
                "parameters": [
                    {
                        "description": "当前登陆用户系统编号",
                        "in": "header",
                        "name": "uid",
                        "required": false,
                        "type": "string"
                    },
                    {
                        "description": "unionId",
                        "in": "query",
                        "name": "unionId",
                        "required": true,
                        "type": "string"
                    },
                    {
                        "description": "channel",
                        "in": "query",
                        "name": "channel",
                        "required": true,
                        "type": "string"
                    }
                ],
                "produces": [
                    "*/*"
                ],
                "responses": {
                    "200": {
                        "description": "OK",
                        "schema": {
                            "$ref": "#/definitions/CommonResponse«string»"
                        }
                    },
                    "401": {
                        "description": "Unauthorized"
                    },
                    "403": {
                        "description": "Forbidden"
                    },
                    "404": {
                        "description": "Not Found"
                    }
                },
                "summary": "getDefaultCardByThirdUnionId",
                "tags": [
                    "myaccount-portal-feign-controller"
                ]
            }
        },
        "/v1/omni/crm/hub/feign/register/pink/card": {
            "post": {
                "consumes": [
                    "application/json"
                ],
                "description": "通过手机号和渠道注册粉卡，如果有门店信息，可传递门店信息",
                "operationId": "registerNewPinkCardUsingPOST",
                "parameters": [
                    {
                        "description": "当前登陆用户系统编号",
                        "in": "header",
                        "name": "uid",
                        "required": false,
                        "type": "string"
                    },
                    {
                        "description": "registerNewPinkCardDTO",
                        "in": "body",
                        "name": "registerNewPinkCardDTO",
                        "required": true,
                        "schema": {
                            "$ref": "#/definitions/RegisterNewPinkCardDTO"
                        }
                    }
                ],
                "produces": [
                    "*/*"
                ],
                "responses": {
                    "200": {
                        "description": "OK",
                        "schema": {
                            "$ref": "#/definitions/CommonResponse«string»"
                        }
                    },
                    "201": {
                        "description": "Created"
                    },
                    "401": {
                        "description": "Unauthorized"
                    },
                    "403": {
                        "description": "Forbidden"
                    },
                    "404": {
                        "description": "Not Found"
                    }
                },
                "summary": "注册粉卡",
                "tags": [
                    "feign-controller"
                ]
            }
        },
        "/v1/omni/crm/hub/feign/wechat-center/default/card/mobile": {
            "get": {
                "consumes": [
                    "application/json"
                ],
                "description": "通过手机号获取对应的默认卡，没有会员卡则发放一张粉卡并同步至CRM",
                "operationId": "getDefaultCardByParamUsingGET",
                "parameters": [
                    {
                        "description": "当前登陆用户系统编号",
                        "in": "header",
                        "name": "uid",
                        "required": false,
                        "type": "string"
                    },
                    {
                        "description": "mobile",
                        "in": "query",
                        "name": "mobile",
                        "required": true,
                        "type": "string"
                    },
                    {
                        "description": "channel",
                        "in": "query",
                        "name": "channel",
                        "required": true,
                        "type": "string"
                    },
                    {
                        "description": "storeCode",
                        "in": "query",
                        "name": "storeCode",
                        "required": false,
                        "type": "string"
                    }
                ],
                "produces": [
                    "*/*"
                ],
                "responses": {
                    "200": {
                        "description": "OK",
                        "schema": {
                            "$ref": "#/definitions/CommonResponse«string»"
                        }
                    },
                    "401": {
                        "description": "Unauthorized"
                    },
                    "403": {
                        "description": "Forbidden"
                    },
                    "404": {
                        "description": "Not Found"
                    }
                },
                "summary": "根据手机号获取对应的默认卡",
                "tags": [
                    "wechat-center-feign-controller"
                ]
            }
        },
        "/v1/omni/crm/hub/feign/wechat-center/mini/register/info": {
            "post": {
                "consumes": [
                    "application/json"
                ],
                "operationId": "saveWechatMiniRegisterInfoUsingPOST",
                "parameters": [
                    {
                        "description": "当前登陆用户系统编号",
                        "in": "header",
                        "name": "uid",
                        "required": false,
                        "type": "string"
                    },
                    {
                        "description": "requestBody",
                        "in": "body",
                        "name": "requestBody",
                        "required": true,
                        "schema": {
                            "$ref": "#/definitions/WechatMiniUserRegisterInfoDTO"
                        }
                    }
                ],
                "produces": [
                    "*/*"
                ],
                "responses": {
                    "200": {
                        "description": "OK",
                        "schema": {
                            "$ref": "#/definitions/CommonResponse«string»"
                        }
                    },
                    "201": {
                        "description": "Created"
                    },
                    "401": {
                        "description": "Unauthorized"
                    },
                    "403": {
                        "description": "Forbidden"
                    },
                    "404": {
                        "description": "Not Found"
                    }
                },
                "summary": "保存wechat-center推送小程序的注册信息，并推送给CRM",
                "tags": [
                    "wechat-center-feign-controller"
                ]
            }
        },
        "/v1/omni/crm/hub/wechat/mini/register/info": {
            "get": {
                "consumes": [
                    "application/json"
                ],
                "operationId": "getWechatMiniRegisterInfoUsingGET",
                "parameters": [
                    {
                        "description": "当前登陆用户系统编号",
                        "in": "header",
                        "name": "uid",
                        "required": false,
                        "type": "string"
                    },
                    {
                        "description": "mobile",
                        "in": "query",
                        "name": "mobile",
                        "required": true,
                        "type": "string"
                    }
                ],
                "produces": [
                    "*/*"
                ],
                "responses": {
                    "200": {
                        "description": "OK",
                        "schema": {
                            "$ref": "#/definitions/CommonResponse«string»"
                        }
                    },
                    "401": {
                        "description": "Unauthorized"
                    },
                    "403": {
                        "description": "Forbidden"
                    },
                    "404": {
                        "description": "Not Found"
                    }
                },
                "summary": "getWechatMiniRegisterInfo",
                "tags": [
                    "mini-program-controller"
                ]
            }
        }
    },
    "swagger": "2.0",
    "tags": [
        {
            "description": "Myaccount Portal Feign Controller",
            "name": "myaccount-portal-feign-controller"
        },
        {
            "description": "Cache Manager Controller",
            "name": "cache-manager-controller"
        },
        {
            "description": "Card Controller",
            "name": "card-controller"
        },
        {
            "description": "Mini Program Controller",
            "name": "mini-program-controller"
        },
        {
            "description": "Beauty Kol Controller",
            "name": "beauty-kol-controller"
        },
        {
            "description": "Wechat Center Feign Controller",
            "name": "wechat-center-feign-controller"
        },
        {
            "description": "Feign Controller",
            "name": "feign-controller"
        }
    ]
}